kozmoml_supervisor_explain/__init__.py
kozmoml_supervisor_explain/common.py
kozmoml_supervisor_explain/errors.py
kozmoml_supervisor_explain/explainers/__init__.py
kozmoml_supervisor_explain/explainers/black_box_runtime.py
kozmoml_supervisor_explain/explainers/integrated_gradients.py
kozmoml_supervisor_explain/explainers/sklearn_api_runtime.py
kozmoml_supervisor_explain/explainers/white_box_runtime.py
kozmoml_supervisor_explain/runtime.py
kozmoml_supervisor_explain/supervisor_dependency_reference.py
kozmoml_supervisor_explain/version.py
kozmoml_supervisor_explain-0.1.0.dev1.dist-info/LICENSE
kozmoml_supervisor_explain-0.1.0.dev1.dist-info/METADATA
kozmoml_supervisor_explain-0.1.0.dev1.dist-info/WHEEL
kozmoml_supervisor_explain-0.1.0.dev1.dist-info/RECORD
